[
  { "questionId": 0, "timestamp": 2000 },
  { "questionId": 1, "timestamp": 4000 },
  { "questionId": 2, "timestamp": 5000 },
  { "questionId": 3, "timestamp": 6000 },
  { "questionId": 4, "timestamp": 7000 },
  { "questionId": 5, "timestamp": 9000 },
  { "questionId": 6, "timestamp": 10000 },
  { "questionId": 7, "timestamp": 12000 },
  { "questionId": 8, "timestamp": 13000 },
  { "questionId": 9, "timestamp": 15000 },
  { "questionId": 10, "timestamp": 16000 },
  { "questionId": 11, "timestamp": 18000 },
  { "questionId": 12, "timestamp": 20000 },
  { "questionId": 13, "timestamp": 22000 }
]
